README.txt
setup.py
collective/__init__.py
collective.subrip2html.egg-info/PKG-INFO
collective.subrip2html.egg-info/SOURCES.txt
collective.subrip2html.egg-info/dependency_links.txt
collective.subrip2html.egg-info/entry_points.txt
collective.subrip2html.egg-info/namespace_packages.txt
collective.subrip2html.egg-info/not-zip-safe
collective.subrip2html.egg-info/requires.txt
collective.subrip2html.egg-info/top_level.txt
collective/subrip2html/__init__.py
collective/subrip2html/configure.zcml
collective/subrip2html/mimetype.py
collective/subrip2html/setuphandlers.py
collective/subrip2html/transform.py
collective/subrip2html/browser/__init__.py
collective/subrip2html/browser/configure.zcml
collective/subrip2html/browser/view.pt
collective/subrip2html/browser/view.py
collective/subrip2html/profiles/default/collective.subrip2html_various.txt
collective/subrip2html/profiles/default/import_steps.xml
collective/subrip2html/profiles/default/metadata.xml
collective/subrip2html/tests/__init__.py
collective/subrip2html/tests/test.srt
collective/subrip2html/tests/test_setup.py
docs/HISTORY.txt
docs/INSTALL.txt
docs/LICENSE.GPL
docs/LICENSE.txt