Metadata-Version: 1.0
Name: collective.subrip2html
Version: 0.1.0a
Summary: A Plone module to add conversion from SRT format to HTML in portal_transforms tool
Home-page: http://svn.plone.org/svn/collective/collective.subrip2html
Author: keul
Author-email: luca@keul.it
License: GPL
Keywords: plone srt html transform subrip
Platform: UNKNOWN
Classifier: Framework :: Plone
Classifier: Programming Language :: Python
Classifier: Topic :: Multimedia :: Video
Classifier: Development Status :: 3 - Alpha
Classifier: Topic :: Text Processing :: Markup
